README.md
setup.py
collision/__init__.py
collision/circle.py
collision/poly.py
collision/response.py
collision/tests.py
collision/tripy.py
collision/util.py
collision.egg-info/PKG-INFO
collision.egg-info/SOURCES.txt
collision.egg-info/dependency_links.txt
collision.egg-info/top_level.txt
collision.egg-info/zip-safe