Metadata-Version: 2.1
Name: collision
Version: 1.2.2
Summary: Collision is a python library meant for collision detection between convex and concave polygons, circles, and points.
Home-page: https://github.com/QwekoDev/collision/
Author: qwertyquerty
License: MIT
Keywords: python collision detection polygon concave convex circle physics game
Platform: Windows
Platform: Linux
Platform: OSX
Requires-Python: >=2.7
